kohakuvault-0.7.1.dist-info/METADATA
kohakuvault-0.7.1.dist-info/WHEEL
kohakuvault-0.7.1.dist-info/licenses/LICENSE
kohakuvault/__init__.py
kohakuvault/_kvault.cpython-310-darwin.so
kohakuvault/_kvault.pyi
kohakuvault/_kvault_csbtree.pyi
kohakuvault/_kvault_skiplist.pyi
kohakuvault/column_proxy.py
kohakuvault/errors.py
kohakuvault/proxy.py
kohakuvault/py.typed
kohakuvault/vector_proxy.py
kohakuvault/wrappers.py
kohakuvault-0.7.1.dist-info/RECORD
