Metadata-Version: 2.4
Name: kohakuvault
Version: 0.7.1
Classifier: Programming Language :: Python :: 3
Classifier: Programming Language :: Python :: 3.10
Classifier: Programming Language :: Python :: 3.11
Classifier: Programming Language :: Python :: 3.12
Classifier: Programming Language :: Python :: 3.13
Classifier: Programming Language :: Rust
Classifier: License :: OSI Approved :: Apache Software License
Classifier: Operating System :: OS Independent
Classifier: Topic :: Database
Classifier: Topic :: Software Development :: Libraries :: Python Modules
Requires-Dist: numpy>=1.20.0
Requires-Dist: maturin>=1.0,<2.0 ; extra == 'dev'
Requires-Dist: black>=23.0.0 ; extra == 'dev'
Requires-Dist: pytest>=7.4.0 ; extra == 'dev'
Requires-Dist: pytest-cov>=4.1.0 ; extra == 'dev'
Requires-Dist: pytest>=7.4.0 ; extra == 'test'
Requires-Dist: pytest-cov>=4.1.0 ; extra == 'test'
Provides-Extra: dev
Provides-Extra: test
License-File: LICENSE
Summary: SQLite-backed KV store (Rust+PyO3) with vector search, auto-packing, and efficient array storage
Author: KohakuVault Contributors
License: Apache-2.0
Requires-Python: >=3.10
